ppvideo/LICENSE
ppvideo/MANIFEST.in
ppvideo/README.md
ppvideo/__init__.py
ppvideo/data/k400/Kinetics-400_label_list.txt
ppvideo/paddlevideo/__init__.py
ppvideo/paddlevideo/version.py
ppvideo/paddlevideo/loader/__init__.py
ppvideo/paddlevideo/loader/builder.py
ppvideo/paddlevideo/loader/dali_loader.py
ppvideo/paddlevideo/loader/registry.py
ppvideo/paddlevideo/loader/dataset/__init__.py
ppvideo/paddlevideo/loader/dataset/base.py
ppvideo/paddlevideo/loader/dataset/bmn_dataset.py
ppvideo/paddlevideo/loader/dataset/feature.py
ppvideo/paddlevideo/loader/dataset/frame.py
ppvideo/paddlevideo/loader/dataset/slowfast_video.py
ppvideo/paddlevideo/loader/dataset/video.py
ppvideo/paddlevideo/loader/pipelines/__init__.py
ppvideo/paddlevideo/loader/pipelines/anet_pipeline.py
ppvideo/paddlevideo/loader/pipelines/augmentations.py
ppvideo/paddlevideo/loader/pipelines/compose.py
ppvideo/paddlevideo/loader/pipelines/decode.py
ppvideo/paddlevideo/loader/pipelines/decode_sampler.py
ppvideo/paddlevideo/loader/pipelines/mix.py
ppvideo/paddlevideo/loader/pipelines/sample.py
ppvideo/paddlevideo/metrics/__init__.py
ppvideo/paddlevideo/metrics/base.py
ppvideo/paddlevideo/metrics/bmn_metric.py
ppvideo/paddlevideo/metrics/build.py
ppvideo/paddlevideo/metrics/center_crop_metric.py
ppvideo/paddlevideo/metrics/multi_crop_metric.py
ppvideo/paddlevideo/metrics/registry.py
ppvideo/paddlevideo/metrics/youtube8m/__init__.py
ppvideo/paddlevideo/metrics/youtube8m/average_precision_calculator.py
ppvideo/paddlevideo/metrics/youtube8m/eval_util.py
ppvideo/paddlevideo/metrics/youtube8m/mean_average_precision_calculator.py
ppvideo/paddlevideo/modeling/__init__.py
ppvideo/paddlevideo/modeling/builder.py
ppvideo/paddlevideo/modeling/registry.py
ppvideo/paddlevideo/modeling/weight_init.py
ppvideo/paddlevideo/modeling/backbones/__init__.py
ppvideo/paddlevideo/modeling/backbones/bmn.py
ppvideo/paddlevideo/modeling/backbones/resnet.py
ppvideo/paddlevideo/modeling/backbones/resnet_slowfast.py
ppvideo/paddlevideo.egg-info/PKG-INFO
ppvideo/paddlevideo.egg-info/SOURCES.txt
ppvideo/paddlevideo.egg-info/dependency_links.txt
ppvideo/paddlevideo.egg-info/entry_points.txt
ppvideo/paddlevideo.egg-info/requires.txt
ppvideo/paddlevideo.egg-info/top_level.txt
paddlevideo-0.0.1.dist-info/LICENSE
paddlevideo-0.0.1.dist-info/METADATA
paddlevideo-0.0.1.dist-info/WHEEL
paddlevideo-0.0.1.dist-info/entry_points.txt
paddlevideo-0.0.1.dist-info/top_level.txt
paddlevideo-0.0.1.dist-info/RECORD
